cfts/__init__.py
cfts/version.py
cfts/app/exp_launcher_gui.enaml
cfts/app/main.py
cfts/paradigms/__init__.py
cfts/paradigms/abr_base.enaml
cfts/paradigms/abr_io.enaml
cfts/paradigms/cfts_mixins.enaml
cfts/paradigms/dpgram.enaml
cfts/paradigms/dpoae_base.enaml
cfts/paradigms/dpoae_io.enaml
cfts/paradigms/dpoae_mixins.enaml
cfts/paradigms/efr.enaml
cfts/paradigms/efr_epochs.enaml
cfts/paradigms/memr.enaml
cfts/paradigms/metadata_mixins.enaml
cfts/paradigms/monitor.enaml
cfts/paradigms/turntable.enaml
cfts/paradigms/video.enaml
cfts-0.1.2.dist-info/LICENSE.txt
cfts-0.1.2.dist-info/METADATA
cfts-0.1.2.dist-info/WHEEL
cfts-0.1.2.dist-info/entry_points.txt
cfts-0.1.2.dist-info/top_level.txt
cfts-0.1.2.dist-info/RECORD
