Metadata-Version: 2.2
Name: cfts
Version: 0.1.2
Summary: Paradigms for running auditory function tests using psiexperiment
Author-email: Brad Buran <buran@ohsu.edu>
Maintainer-email: Brad Buran <buran@ohsu.edu>
License: MIT License
Requires-Python: >=3.7
License-File: LICENSE.txt
Requires-Dist: cftscal
Requires-Dist: cftsdata
Requires-Dist: psiexperiment[zarr]
Requires-Dist: enaml[qt6-pyside]>=0.13.0
Requires-Dist: enamlx>=0.6.2
Requires-Dist: tqdm
Provides-Extra: ni
Requires-Dist: psiexperiment[ni]; extra == "ni"
Provides-Extra: tdt
Requires-Dist: psiexperiment[tdt]; extra == "tdt"
Provides-Extra: docs
Requires-Dist: sphinx; extra == "docs"
Requires-Dist: sphinx_rtd_theme; extra == "docs"
Requires-Dist: pygments-enaml; extra == "docs"
Provides-Extra: test
Requires-Dist: pytest; extra == "test"
Requires-Dist: pytest-console-scripts; extra == "test"
Requires-Dist: matplotlib; extra == "test"
Provides-Extra: dev
Requires-Dist: coloredlogs; extra == "dev"
